piragi/__init__.py
piragi/async_ragi.py
piragi/async_updater.py
piragi/change_detection.py
piragi/chunking.py
piragi/core.py
piragi/embeddings.py
piragi/hybrid_search.py
piragi/knowledge_graph.py
piragi/loader.py
piragi/query_transform.py
piragi/reranker.py
piragi/retrieval.py
piragi/semantic_chunking.py
piragi/store.py
piragi/types.py
piragi/stores/__init__.py
piragi/stores/factory.py
piragi/stores/lance.py
piragi/stores/pinecone.py
piragi/stores/postgres.py
piragi/stores/protocol.py
piragi/stores/supabase.py
piragi-0.7.8.dist-info/METADATA
piragi-0.7.8.dist-info/WHEEL
piragi-0.7.8.dist-info/licenses/LICENSE
piragi-0.7.8.dist-info/RECORD
