Metadata-Version: 2.4
Name: piragi
Version: 0.7.8
Summary: The best RAG interface yet - Built-in vector store, embeddings, citations, and auto-updates
Project-URL: Homepage, https://github.com/hemanth/ragi
Project-URL: Documentation, https://github.com/hemanth/ragi#readme
Project-URL: Repository, https://github.com/hemanth/ragi
Project-URL: Issues, https://github.com/hemanth/ragi/issues
Author-email: Hemanth HM <hemanth.hm@gmail.com>
License-Expression: MIT
License-File: LICENSE
Keywords: ai,embeddings,llm,rag,retrieval,vector-search
Classifier: Development Status :: 3 - Alpha
Classifier: Intended Audience :: Developers
Classifier: License :: OSI Approved :: MIT License
Classifier: Programming Language :: Python :: 3
Classifier: Programming Language :: Python :: 3.10
Classifier: Programming Language :: Python :: 3.11
Classifier: Programming Language :: Python :: 3.12
Requires-Python: >=3.10
Requires-Dist: lancedb>=0.3.0
Requires-Dist: markitdown[all]>=0.0.1
Requires-Dist: openai>=1.0.0
Requires-Dist: pyarrow>=14.0.0
Requires-Dist: pydantic>=2.0.0
Requires-Dist: pysbd>=0.3.4
Requires-Dist: python-dotenv>=1.0.0
Requires-Dist: scikit-learn>=1.0.0
Requires-Dist: sentence-transformers>=2.2.0
Requires-Dist: torch>=2.0.0
Requires-Dist: transformers>=4.51.0
Provides-Extra: all
Requires-Dist: adlfs>=2023.1.0; extra == 'all'
Requires-Dist: crawl4ai>=0.4.0; extra == 'all'
Requires-Dist: fsspec>=2023.1.0; extra == 'all'
Requires-Dist: gcsfs>=2023.1.0; extra == 'all'
Requires-Dist: networkx>=3.0; extra == 'all'
Requires-Dist: pgvector>=0.2.0; extra == 'all'
Requires-Dist: pinecone-client>=3.0.0; extra == 'all'
Requires-Dist: psycopg2-binary>=2.9.0; extra == 'all'
Requires-Dist: s3fs>=2023.1.0; extra == 'all'
Requires-Dist: supabase>=2.0.0; extra == 'all'
Provides-Extra: azure
Requires-Dist: adlfs>=2023.1.0; extra == 'azure'
Requires-Dist: fsspec>=2023.1.0; extra == 'azure'
Provides-Extra: crawler
Requires-Dist: crawl4ai>=0.4.0; extra == 'crawler'
Provides-Extra: dev
Requires-Dist: black>=23.0.0; extra == 'dev'
Requires-Dist: mypy>=1.0.0; extra == 'dev'
Requires-Dist: pytest-asyncio>=0.21.0; extra == 'dev'
Requires-Dist: pytest-cov>=4.0.0; extra == 'dev'
Requires-Dist: pytest>=7.0.0; extra == 'dev'
Requires-Dist: ruff>=0.1.0; extra == 'dev'
Provides-Extra: gcs
Requires-Dist: fsspec>=2023.1.0; extra == 'gcs'
Requires-Dist: gcsfs>=2023.1.0; extra == 'gcs'
Provides-Extra: graph
Requires-Dist: networkx>=3.0; extra == 'graph'
Provides-Extra: pinecone
Requires-Dist: pinecone-client>=3.0.0; extra == 'pinecone'
Provides-Extra: postgres
Requires-Dist: pgvector>=0.2.0; extra == 'postgres'
Requires-Dist: psycopg2-binary>=2.9.0; extra == 'postgres'
Provides-Extra: remote
Requires-Dist: adlfs>=2023.1.0; extra == 'remote'
Requires-Dist: fsspec>=2023.1.0; extra == 'remote'
Requires-Dist: gcsfs>=2023.1.0; extra == 'remote'
Requires-Dist: s3fs>=2023.1.0; extra == 'remote'
Provides-Extra: s3
Requires-Dist: fsspec>=2023.1.0; extra == 's3'
Requires-Dist: s3fs>=2023.1.0; extra == 's3'
Provides-Extra: supabase
Requires-Dist: supabase>=2.0.0; extra == 'supabase'
